{"title": "2025-26 Stony Brook Seawolves Roster", "groups": [{"template": "table-roster", "headers": [{"columns": [{"index": 0, "text": "GUARD", "priority": 1, "template": "cell-entity-text", "weight": 4.9, "emphasized": true, "sortable": "none"}, {"index": 1, "text": "POS", "priority": 2, "template": "cell-text", "weight": 1, "emphasized": false, "sortable": "none"}, {"index": 2, "text": "CLS", "priority": 3, "template": "cell-text", "weight": 1.1, "emphasized": false, "sortable": "none"}, {"index": 3, "text": "HT", "priority": 4, "template": "cell-text", "weight": 1.2, "emphasized": false, "sortable": "none"}, {"index": 4, "text": "WT", "priority": 5, "template": "cell-text", "weight": 1.8, "emphasized": false, "sortable": "none"}], "isPrimary": true}], "rows": [{"columns": [{"index": 0, "text": "Rob Brown III", "superscript": "#2", "emphasized": false}, {"index": 1, "text": "G", "emphasized": false}, {"index": 2, "text": "GS", "emphasized": false}, {"index": 3, "text": "6'4\"", "emphasized": false}, {"index": 4, "text": "195 lbs", "emphasized": false}], "isCutoff": false, "selected": false, "entityLink": {"title": "ROB BROWN III", "webUrl": "/college-basketball/rob-brown-2-player", "color": "1, 153, 27, 30", "imageUrl": "https://b.fssta.com/uploads/application/college/team-logos/StonyBrook.vresize.200.200.medium.1.png", "imageType": "image-logo", "imageAltText": "Stony Brook Seawolves", "contentUri": "basketball/cbk/athletes/60082", "contentType": "athlete", "layout": {"path": "/layouts?type=layout&subtype=playersLayout&elementId=cbk", "tokens": {"id": "60082", "contentUri": "basketball/cbk/athletes/60082"}}, "analyticsName": "rob-brown-2", "analyticsSport": "college-basketball", "type": "entity"}, "isFaded": false}, {"columns": [{"index": 0, "text": "Jonah Butler", "superscript": "#5", "emphasized": false}, {"index": 1, "text": "G", "emphasized": false}, {"index": 2, "text": "FR", "emphasized": false}, {"index": 3, "text": "6'6\"", "emphasized": false}, {"index": 4, "text": "210 lbs", "emphasized": false}], "isCutoff": false, "selected": false, "entityLink": {"title": "JONAH BUTLER", "webUrl": "/college-basketball/jonah-butler-player", "color": "1, 153, 27, 30", "imageUrl": "https://b.fssta.com/uploads/application/college/team-logos/StonyBrook.vresize.200.200.medium.1.png", "imageType": "image-logo", "imageAltText": "Stony Brook Seawolves", "contentUri": "basketball/cbk/athletes/82504", "contentType": "athlete", "layout": {"path": "/layouts?type=layout&subtype=playersLayout&elementId=cbk", "tokens": {"id": "82504", "contentUri": "basketball/cbk/athletes/82504"}}, "analyticsName": "jonah-butler", "analyticsSport": "college-basketball", "type": "entity"}, "isFaded": false}, {"columns": [{"index": 0, "text": "Liam Dagostino", "superscript": "#6", "emphasized": false}, {"index": 1, "text": "G", "emphasized": false}, {"index": 2, "text": "FR", "emphasized": false}, {"index": 3, "text": "6'5\"", "emphasized": false}, {"index": 4, "text": "180 lbs", "emphasized": false}], "isCutoff": false, "selected": false, "entityLink": {"title": "LIAM DAGOSTINO", "webUrl": "/college-basketball/liam-dagostino-player", "color": "1, 153, 27, 30", "imageUrl": "https://b.fssta.com/uploads/application/college/team-logos/StonyBrook.vresize.200.200.medium.1.png", "imageType": "image-logo", "imageAltText": "Stony Brook Seawolves", "contentUri": "basketball/cbk/athletes/82502", "contentType": "athlete", "layout": {"path": "/layouts?type=layout&subtype=playersLayout&elementId=cbk", "tokens": {"id": "82502", "contentUri": "basketball/cbk/athletes/82502"}}, "analyticsName": "liam-dagostino", "analyticsSport": "college-basketball", "type": "entity"}, "isFaded": false}, {"columns": [{"index": 0, "text": "Jake Harbatkin", "superscript": "#11", "emphasized": false}, {"index": 1, "text": "G", "emphasized": false}, {"index": 2, "text": "FR", "emphasized": false}, {"index": 3, "text": "6'3\"", "emphasized": false}, {"index": 4, "text": "185 lbs", "emphasized": false}], "isCutoff": false, "selected": false, "entityLink": {"title": "JAKE HARBATKIN", "webUrl": "/college-basketball/jake-harbatkin-player", "color": "1, 153, 27, 30", "imageUrl": "https://b.fssta.com/uploads/application/college/team-logos/StonyBrook.vresize.200.200.medium.1.png", "imageType": "image-logo", "imageAltText": "Stony Brook Seawolves", "contentUri": "basketball/cbk/athletes/82500", "contentType": "athlete", "layout": {"path": "/layouts?type=layout&subtype=playersLayout&elementId=cbk", "tokens": {"id": "82500", "contentUri": "basketball/cbk/athletes/82500"}}, "analyticsName": "jake-harbatkin", "analyticsSport": "college-basketball", "type": "entity"}, "isFaded": false}, {"columns": [{"index": 0, "text": "Collin O'Connor", "superscript": "#13", "emphasized": false}, {"index": 1, "text": "G", "emphasized": false}, {"index": 2, "text": "SO", "emphasized": false}, {"index": 3, "text": "6'3\"", "emphasized": false}, {"index": 4, "text": "195 lbs", "emphasized": false}], "isCutoff": false, "selected": false, "entityLink": {"title": "COLLIN O'CONNOR", "webUrl": "/college-basketball/collin-oconnor-player", "color": "1, 153, 27, 30", "imageUrl": "https://b.fssta.com/uploads/application/college/team-logos/StonyBrook.vresize.200.200.medium.1.png", "imageType": "image-logo", "imageAltText": "Stony Brook Seawolves", "contentUri": "basketball/cbk/athletes/77125", "contentType": "athlete", "layout": {"path": "/layouts?type=layout&subtype=playersLayout&elementId=cbk", "tokens": {"id": "77125", "contentUri": "basketball/cbk/athletes/77125"}}, "analyticsName": "collin-oconnor", "analyticsSport": "college-basketball", "type": "entity"}, "isFaded": false}, {"columns": [{"index": 0, "text": "Toby Onyekonwu", "superscript": "#4", "emphasized": false}, {"index": 1, "text": "G", "emphasized": false}, {"index": 2, "text": "SR", "emphasized": false}, {"index": 3, "text": "6'2\"", "emphasized": false}, {"index": 4, "text": "170 lbs", "emphasized": false}], "isCutoff": false, "selected": false, "entityLink": {"title": "TOBY ONYEKONWU", "webUrl": "/college-basketball/toby-onyekonwu-player", "color": "1, 153, 27, 30", "imageUrl": "https://b.fssta.com/uploads/application/college/team-logos/StonyBrook.vresize.200.200.medium.1.png", "imageType": "image-logo", "imageAltText": "Stony Brook Seawolves", "contentUri": "basketball/cbk/athletes/65489", "contentType": "athlete", "layout": {"path": "/layouts?type=layout&subtype=playersLayout&elementId=cbk", "tokens": {"id": "65489", "contentUri": "basketball/cbk/athletes/65489"}}, "analyticsName": "toby-onyekonwu", "analyticsSport": "college-basketball", "type": "entity"}, "isFaded": false}, {"columns": [{"index": 0, "text": "Erik Pratt", "superscript": "#1", "emphasized": false}, {"index": 1, "text": "G", "emphasized": false}, {"index": 2, "text": "GS", "emphasized": false}, {"index": 3, "text": "6'5\"", "emphasized": false}, {"index": 4, "text": "185 lbs", "emphasized": false}], "isCutoff": false, "selected": false, "entityLink": {"title": "ERIK PRATT", "webUrl": "/college-basketball/erik-pratt-player", "color": "1, 153, 27, 30", "imageUrl": "https://b.fssta.com/uploads/application/college/team-logos/StonyBrook.vresize.200.200.medium.1.png", "imageType": "image-logo", "imageAltText": "Stony Brook Seawolves", "contentUri": "basketball/cbk/athletes/65255", "contentType": "athlete", "layout": {"path": "/layouts?type=layout&subtype=playersLayout&elementId=cbk", "tokens": {"id": "65255", "contentUri": "basketball/cbk/athletes/65255"}}, "analyticsName": "erik-pratt", "analyticsSport": "college-basketball", "type": "entity"}, "isFaded": false}, {"columns": [{"index": 0, "text": "Andrej Shoshkikj", "superscript": "#29", "emphasized": false}, {"index": 1, "text": "G", "emphasized": false}, {"index": 2, "text": "FR", "emphasized": false}, {"index": 3, "text": "6'2\"", "emphasized": false}, {"index": 4, "text": "182 lbs", "emphasized": false}], "isCutoff": false, "selected": false, "entityLink": {"title": "ANDREJ SHOSHKIKJ", "webUrl": "/college-basketball/andrej-shoshkikj-player", "color": "1, 153, 27, 30", "imageUrl": "https://b.fssta.com/uploads/application/college/team-logos/StonyBrook.vresize.200.200.medium.1.png", "imageType": "image-logo", "imageAltText": "Stony Brook Seawolves", "contentUri": "basketball/cbk/athletes/82498", "contentType": "athlete", "layout": {"path": "/layouts?type=layout&subtype=playersLayout&elementId=cbk", "tokens": {"id": "82498", "contentUri": "basketball/cbk/athletes/82498"}}, "analyticsName": "andrej-shoshkikj", "analyticsSport": "college-basketball", "type": "entity"}, "isFaded": false}, {"columns": [{"index": 0, "text": "Ethan Simmon", "superscript": "#7", "emphasized": false}, {"index": 1, "text": "G", "emphasized": false}, {"index": 2, "text": "SR", "emphasized": false}, {"index": 3, "text": "6'5\"", "emphasized": false}, {"index": 4, "text": "205 lbs", "emphasized": false}], "isCutoff": false, "selected": false, "entityLink": {"title": "ETHAN SIMMON", "webUrl": "/college-basketball/ethan-simmon-player", "color": "1, 153, 27, 30", "imageUrl": "https://b.fssta.com/uploads/application/college/team-logos/StonyBrook.vresize.200.200.medium.1.png", "imageType": "image-logo", "imageAltText": "Stony Brook Seawolves", "contentUri": "basketball/cbk/athletes/82501", "contentType": "athlete", "layout": {"path": "/layouts?type=layout&subtype=playersLayout&elementId=cbk", "tokens": {"id": "82501", "contentUri": "basketball/cbk/athletes/82501"}}, "analyticsName": "ethan-simmon", "analyticsSport": "college-basketball", "type": "entity"}, "isFaded": false}]}, {"template": "table-roster", "headers": [{"columns": [{"index": 0, "text": "FORWARD", "priority": 1, "template": "cell-entity-text", "weight": 4.9, "emphasized": true, "sortable": "none"}, {"index": 1, "text": "POS", "priority": 2, "template": "cell-text", "weight": 1, "emphasized": false, "sortable": "none"}, {"index": 2, "text": "CLS", "priority": 3, "template": "cell-text", "weight": 1.1, "emphasized": false, "sortable": "none"}, {"index": 3, "text": "HT", "priority": 4, "template": "cell-text", "weight": 1.2, "emphasized": false, "sortable": "none"}, {"index": 4, "text": "WT", "priority": 5, "template": "cell-text", "weight": 1.8, "emphasized": false, "sortable": "none"}], "isPrimary": true}], "rows": [{"columns": [{"index": 0, "text": "Richard Goods", "superscript": "#12", "emphasized": false}, {"index": 1, "text": "F", "emphasized": false}, {"index": 2, "text": "SO", "emphasized": false}, {"index": 3, "text": "6'9\"", "emphasized": false}, {"index": 4, "text": "225 lbs", "emphasized": false}], "isCutoff": false, "selected": false, "entityLink": {"title": "RICHARD GOODS", "webUrl": "/college-basketball/richard-goods-player", "color": "1, 153, 27, 30", "imageUrl": "https://b.fssta.com/uploads/application/college/team-logos/StonyBrook.vresize.200.200.medium.1.png", "imageType": "image-logo", "imageAltText": "Stony Brook Seawolves", "contentUri": "basketball/cbk/athletes/77119", "contentType": "athlete", "layout": {"path": "/layouts?type=layout&subtype=playersLayout&elementId=cbk", "tokens": {"id": "77119", "contentUri": "basketball/cbk/athletes/77119"}}, "analyticsName": "richard-goods", "analyticsSport": "college-basketball", "type": "entity"}, "isFaded": false}, {"columns": [{"index": 0, "text": "Quin Gorman", "superscript": "#15", "emphasized": false}, {"index": 1, "text": "F", "emphasized": false}, {"index": 2, "text": "SO", "emphasized": false}, {"index": 3, "text": "6'8\"", "emphasized": false}, {"index": 4, "text": "210 lbs", "emphasized": false}], "isCutoff": false, "selected": false, "entityLink": {"title": "QUIN GORMAN", "webUrl": "/college-basketball/quin-gorman-player", "color": "1, 153, 27, 30", "imageUrl": "https://b.fssta.com/uploads/application/college/team-logos/StonyBrook.vresize.200.200.medium.1.png", "imageType": "image-logo", "imageAltText": "Stony Brook Seawolves", "contentUri": "basketball/cbk/athletes/77128", "contentType": "athlete", "layout": {"path": "/layouts?type=layout&subtype=playersLayout&elementId=cbk", "tokens": {"id": "77128", "contentUri": "basketball/cbk/athletes/77128"}}, "analyticsName": "quin-gorman", "analyticsSport": "college-basketball", "type": "entity"}, "isFaded": false}, {"columns": [{"index": 0, "text": "Oleg Kojenets", "superscript": "#17", "emphasized": false}, {"index": 1, "text": "F", "emphasized": false}, {"index": 2, "text": "GS", "emphasized": false}, {"index": 3, "text": "7'0\"", "emphasized": false}, {"index": 4, "text": "228 lbs", "emphasized": false}], "isCutoff": false, "selected": false, "entityLink": {"title": "OLEG KOJENETS", "webUrl": "/college-basketball/oleg-kojenets-player", "color": "1, 153, 27, 30", "imageUrl": "https://b.fssta.com/uploads/application/college/team-logos/StonyBrook.vresize.200.200.medium.1.png", "imageType": "image-logo", "imageAltText": "Stony Brook Seawolves", "contentUri": "basketball/cbk/athletes/59756", "contentType": "athlete", "layout": {"path": "/layouts?type=layout&subtype=playersLayout&elementId=cbk", "tokens": {"id": "59756", "contentUri": "basketball/cbk/athletes/59756"}}, "analyticsName": "oleg-kojenets", "analyticsSport": "college-basketball", "type": "entity"}, "isFaded": false}, {"columns": [{"index": 0, "text": "Leon Nahar", "superscript": "#33", "emphasized": false}, {"index": 1, "text": "F", "emphasized": false}, {"index": 2, "text": "JR", "emphasized": false}, {"index": 3, "text": "6'10\"", "emphasized": false}, {"index": 4, "text": "218 lbs", "emphasized": false}], "isCutoff": false, "selected": false, "entityLink": {"title": "LEON NAHAR", "webUrl": "/college-basketball/leon-nahar-player", "color": "1, 153, 27, 30", "imageUrl": "https://b.fssta.com/uploads/application/college/team-logos/StonyBrook.vresize.200.200.medium.1.png", "imageType": "image-logo", "imageAltText": "Stony Brook Seawolves", "contentUri": "basketball/cbk/athletes/65491", "contentType": "athlete", "layout": {"path": "/layouts?type=layout&subtype=playersLayout&elementId=cbk", "tokens": {"id": "65491", "contentUri": "basketball/cbk/athletes/65491"}}, "analyticsName": "leon-nahar", "analyticsSport": "college-basketball", "type": "entity"}, "isFaded": false}, {"columns": [{"index": 0, "text": "Andrew Okafor", "superscript": "#10", "emphasized": false}, {"index": 1, "text": "F", "emphasized": false}, {"index": 2, "text": "FR", "emphasized": false}, {"index": 3, "text": "6'8\"", "emphasized": false}, {"index": 4, "text": "205 lbs", "emphasized": false}], "isCutoff": false, "selected": false, "entityLink": {"title": "ANDREW OKAFOR", "webUrl": "/college-basketball/andrew-okafor-player", "color": "1, 153, 27, 30", "imageUrl": "https://b.fssta.com/uploads/application/college/team-logos/StonyBrook.vresize.200.200.medium.1.png", "imageType": "image-logo", "imageAltText": "Stony Brook Seawolves", "contentUri": "basketball/cbk/athletes/82503", "contentType": "athlete", "layout": {"path": "/layouts?type=layout&subtype=playersLayout&elementId=cbk", "tokens": {"id": "82503", "contentUri": "basketball/cbk/athletes/82503"}}, "analyticsName": "andrew-okafor", "analyticsSport": "college-basketball", "type": "entity"}, "isFaded": false}, {"columns": [{"index": 0, "text": "Tomas Valentiny", "superscript": "#21", "emphasized": false}, {"index": 1, "text": "F", "emphasized": false}, {"index": 2, "text": "FR", "emphasized": false}, {"index": 3, "text": "6'6\"", "emphasized": false}, {"index": 4, "text": "201 lbs", "emphasized": false}], "isCutoff": false, "selected": false, "entityLink": {"title": "TOMAS VALENTINY", "webUrl": "/college-basketball/tomas-valentiny-player", "color": "1, 153, 27, 30", "imageUrl": "https://b.fssta.com/uploads/application/college/team-logos/StonyBrook.vresize.200.200.medium.1.png", "imageType": "image-logo", "imageAltText": "Stony Brook Seawolves", "contentUri": "basketball/cbk/athletes/82499", "contentType": "athlete", "layout": {"path": "/layouts?type=layout&subtype=playersLayout&elementId=cbk", "tokens": {"id": "82499", "contentUri": "basketball/cbk/athletes/82499"}}, "analyticsName": "tomas-valentiny", "analyticsSport": "college-basketball", "type": "entity"}, "isFaded": false}]}, {"template": "table-roster", "headers": [{"columns": [{"index": 0, "text": "PLAYER COUNT", "priority": 1, "template": "cell-text", "weight": 2.5, "emphasized": true, "sortable": "none"}, {"index": 1, "priority": 5, "template": "cell-text", "weight": 2.5, "emphasized": false, "sortable": "none", "hideView": 1}, {"index": 2, "text": "AVG AGE", "priority": 2, "template": "cell-text", "weight": 2.5, "emphasized": false, "sortable": "none"}, {"index": 3, "text": "AVG HT", "priority": 3, "template": "cell-text", "weight": 2.5, "emphasized": false, "sortable": "none"}, {"index": 4, "text": "AVG WT", "priority": 4, "template": "cell-text", "weight": 2.5, "emphasized": false, "sortable": "none"}], "isPrimary": true}], "rows": [{"columns": [{"index": 0, "text": "15", "emphasized": false}, {"index": 1, "emphasized": false}, {"index": 2, "text": "-", "emphasized": false}, {"index": 3, "text": "6'5\"", "emphasized": false}, {"index": 4, "text": "199.6 lbs", "emphasized": false}], "isCutoff": false, "selected": false, "isFaded": false}]}]}