[
  {
    "name": "Jermaurhiyun Anderson",
    "jersey": "1",
    "class": "SO"
  },
  {
    "name": "AJ Bates",
    "jersey": "3",
    "class": "SO"
  },
  {
    "name": "Kaden Cooper",
    "jersey": "11",
    "class": "JR"
  },
  {
    "name": "DJ Dudley",
    "jersey": "0",
    "class": "JR"
  },
  {
    "name": "Jaylen Fenner",
    "jersey": "4",
    "class": "FR"
  },
  {
    "name": "Keegan Rowell",
    "jersey": "6",
    "class": "SO"
  },
  {
    "name": "Lachlan Thompson",
    "jersey": "23",
    "class": "SO"
  },
  {
    "name": "Scooter Williams",
    "jersey": "8",
    "class": "GS"
  },
  {
    "name": "Will Allen",
    "jersey": "14",
    "class": "SR"
  },
  {
    "name": "Sir Issac Herron",
    "jersey": "7",
    "class": "GS"
  },
  {
    "name": "Kylan Howze",
    "jersey": "10",
    "class": "JR"
  },
  {
    "name": "Will Jeffress",
    "jersey": "2",
    "class": "GS"
  },
  {
    "name": "Avery Thomas II",
    "jersey": "5",
    "class": "SO"
  },
  {
    "name": "A'Meir Williams",
    "jersey": "27",
    "class": "FR"
  },
  {
    "name": "Melian Martinez",
    "jersey": "21",
    "class": "JR"
  }
]