{"title": "2025-26 Indiana Hoosiers Roster", "groups": [{"template": "table-roster", "headers": [{"columns": [{"index": 0, "text": "GUARD", "priority": 1, "template": "cell-entity-text", "weight": 4.9, "emphasized": true, "sortable": "none"}, {"index": 1, "text": "POS", "priority": 2, "template": "cell-text", "weight": 1, "emphasized": false, "sortable": "none"}, {"index": 2, "text": "CLS", "priority": 3, "template": "cell-text", "weight": 1.1, "emphasized": false, "sortable": "none"}, {"index": 3, "text": "HT", "priority": 4, "template": "cell-text", "weight": 1.2, "emphasized": false, "sortable": "none"}, {"index": 4, "text": "WT", "priority": 5, "template": "cell-text", "weight": 1.8, "emphasized": false, "sortable": "none"}], "isPrimary": true}], "rows": [{"columns": [{"index": 0, "text": "Tayton Conerway", "superscript": "#6", "emphasized": false}, {"index": 1, "text": "G", "emphasized": false}, {"index": 2, "text": "SR", "emphasized": false}, {"index": 3, "text": "6'3\"", "emphasized": false}, {"index": 4, "text": "190 lbs", "emphasized": false}], "isCutoff": false, "selected": false, "entityLink": {"title": "TAYTON CONERWAY", "webUrl": "/college-basketball/tayton-conerway-player", "color": "1, 156, 5, 47", "imageUrl": "https://b.fssta.com/uploads/application/college/team-logos/Indiana-alternate.vresize.200.200.medium.0.png", "imageType": "image-logo", "imageAltText": "Indiana Hoosiers", "contentUri": "basketball/cbk/athletes/70469", "contentType": "athlete", "layout": {"path": "/layouts?type=layout&subtype=playersLayout&elementId=cbk", "tokens": {"id": "70469", "contentUri": "basketball/cbk/athletes/70469"}}, "analyticsName": "tayton-conerway", "analyticsSport": "college-basketball", "type": "entity"}, "isFaded": false}, {"columns": [{"index": 0, "text": "Nick Dorn", "superscript": "#7", "emphasized": false}, {"index": 1, "text": "G", "emphasized": false}, {"index": 2, "text": "JR", "emphasized": false}, {"index": 3, "text": "6'7\"", "emphasized": false}, {"index": 4, "text": "225 lbs", "emphasized": false}], "isCutoff": false, "selected": false, "entityLink": {"title": "NICK DORN", "webUrl": "/college-basketball/nick-dorn-player", "color": "1, 156, 5, 47", "imageUrl": "https://b.fssta.com/uploads/application/college/team-logos/Indiana-alternate.vresize.200.200.medium.0.png", "imageType": "image-logo", "imageAltText": "Indiana Hoosiers", "contentUri": "basketball/cbk/athletes/71647", "contentType": "athlete", "layout": {"path": "/layouts?type=layout&subtype=playersLayout&elementId=cbk", "tokens": {"id": "71647", "contentUri": "basketball/cbk/athletes/71647"}}, "analyticsName": "nick-dorn", "analyticsSport": "college-basketball", "type": "entity"}, "isFaded": false}, {"columns": [{"index": 0, "text": "Jason Drake", "superscript": "#2", "emphasized": false}, {"index": 1, "text": "G", "emphasized": false}, {"index": 2, "text": "JR", "emphasized": false}, {"index": 3, "text": "6'1\"", "emphasized": false}, {"index": 4, "text": "200 lbs", "emphasized": false}], "isCutoff": false, "selected": false, "entityLink": {"title": "JASON DRAKE", "webUrl": "/college-basketball/jason-drake-player", "color": "1, 156, 5, 47", "imageUrl": "https://b.fssta.com/uploads/application/college/team-logos/Indiana-alternate.vresize.200.200.medium.0.png", "imageType": "image-logo", "imageAltText": "Indiana Hoosiers", "contentUri": "basketball/cbk/athletes/65159", "contentType": "athlete", "layout": {"path": "/layouts?type=layout&subtype=playersLayout&elementId=cbk", "tokens": {"id": "65159", "contentUri": "basketball/cbk/athletes/65159"}}, "analyticsName": "jason-drake", "analyticsSport": "college-basketball", "type": "entity"}, "isFaded": false}, {"columns": [{"index": 0, "text": "Conor Enright", "superscript": "#5", "emphasized": false}, {"index": 1, "text": "G", "emphasized": false}, {"index": 2, "text": "SR", "emphasized": false}, {"index": 3, "text": "6'1\"", "emphasized": false}, {"index": 4, "text": "180 lbs", "emphasized": false}], "isCutoff": false, "selected": false, "entityLink": {"title": "CONOR ENRIGHT", "webUrl": "/college-basketball/conor-enright-player", "color": "1, 156, 5, 47", "imageUrl": "https://b.fssta.com/uploads/application/college/team-logos/Indiana-alternate.vresize.200.200.medium.0.png", "imageType": "image-logo", "imageAltText": "Indiana Hoosiers", "contentUri": "basketball/cbk/athletes/58841", "contentType": "athlete", "layout": {"path": "/layouts?type=layout&subtype=playersLayout&elementId=cbk", "tokens": {"id": "58841", "contentUri": "basketball/cbk/athletes/58841"}}, "analyticsName": "conor-enright", "analyticsSport": "college-basketball", "type": "entity"}, "isFaded": false}, {"columns": [{"index": 0, "text": "Tryce Grensing", "superscript": "#18", "emphasized": false}, {"index": 1, "text": "G", "emphasized": false}, {"index": 2, "text": "FR", "emphasized": false}, {"index": 3, "text": "6'0\"", "emphasized": false}, {"index": 4, "text": "175 lbs", "emphasized": false}], "isCutoff": false, "selected": false, "entityLink": {"title": "TRYCE GRENSING", "webUrl": "/college-basketball/tryce-grensing-player", "color": "1, 156, 5, 47", "imageUrl": "https://b.fssta.com/uploads/application/college/team-logos/Indiana-alternate.vresize.200.200.medium.0.png", "imageType": "image-logo", "imageAltText": "Indiana Hoosiers", "contentUri": "basketball/cbk/athletes/81057", "contentType": "athlete", "layout": {"path": "/layouts?type=layout&subtype=playersLayout&elementId=cbk", "tokens": {"id": "81057", "contentUri": "basketball/cbk/athletes/81057"}}, "analyticsName": "tryce-grensing", "analyticsSport": "college-basketball", "type": "entity"}, "isFaded": false}, {"columns": [{"index": 0, "text": "Jasai Miles", "superscript": "#0", "emphasized": false}, {"index": 1, "text": "G", "emphasized": false}, {"index": 2, "text": "JR", "emphasized": false}, {"index": 3, "text": "6'6\"", "emphasized": false}, {"index": 4, "text": "210 lbs", "emphasized": false}], "isCutoff": false, "selected": false, "entityLink": {"title": "JASAI MILES", "webUrl": "/college-basketball/jasai-miles-player", "color": "1, 156, 5, 47", "imageUrl": "https://b.fssta.com/uploads/application/college/team-logos/Indiana-alternate.vresize.200.200.medium.0.png", "imageType": "image-logo", "imageAltText": "Indiana Hoosiers", "contentUri": "basketball/cbk/athletes/71066", "contentType": "athlete", "layout": {"path": "/layouts?type=layout&subtype=playersLayout&elementId=cbk", "tokens": {"id": "71066", "contentUri": "basketball/cbk/athletes/71066"}}, "analyticsName": "jasai-miles", "analyticsSport": "college-basketball", "type": "entity"}, "isFaded": false}, {"columns": [{"index": 0, "text": "Jordan Rayford", "superscript": "#14", "emphasized": false}, {"index": 1, "text": "G", "emphasized": false}, {"index": 2, "text": "JR", "emphasized": false}, {"index": 3, "text": "6'5\"", "emphasized": false}, {"index": 4, "text": "210 lbs", "emphasized": false}], "isCutoff": false, "selected": false, "entityLink": {"title": "JORDAN RAYFORD", "webUrl": "/college-basketball/jordan-rayford-player", "color": "1, 156, 5, 47", "imageUrl": "https://b.fssta.com/uploads/application/college/team-logos/Indiana-alternate.vresize.200.200.medium.0.png", "imageType": "image-logo", "imageAltText": "Indiana Hoosiers", "contentUri": "basketball/cbk/athletes/67548", "contentType": "athlete", "layout": {"path": "/layouts?type=layout&subtype=playersLayout&elementId=cbk", "tokens": {"id": "67548", "contentUri": "basketball/cbk/athletes/67548"}}, "analyticsName": "jordan-rayford", "analyticsSport": "college-basketball", "type": "entity"}, "isFaded": false}, {"columns": [{"index": 0, "text": "Aleksa Ristic", "superscript": "#13", "emphasized": false}, {"index": 1, "text": "G", "emphasized": false}, {"index": 2, "text": "FR", "emphasized": false}, {"index": 3, "text": "6'3\"", "emphasized": false}, {"index": 4, "text": "200 lbs", "emphasized": false}], "isCutoff": false, "selected": false, "entityLink": {"title": "ALEKSA RISTIC", "webUrl": "/college-basketball/aleksa-ristic-player", "color": "1, 156, 5, 47", "imageUrl": "https://b.fssta.com/uploads/application/college/team-logos/Indiana-alternate.vresize.200.200.medium.0.png", "imageType": "image-logo", "imageAltText": "Indiana Hoosiers", "contentUri": "basketball/cbk/athletes/81042", "contentType": "athlete", "layout": {"path": "/layouts?type=layout&subtype=playersLayout&elementId=cbk", "tokens": {"id": "81042", "contentUri": "basketball/cbk/athletes/81042"}}, "analyticsName": "aleksa-ristic", "analyticsSport": "college-basketball", "type": "entity"}, "isFaded": false}, {"columns": [{"index": 0, "text": "Drew Snively", "superscript": "#21", "emphasized": false}, {"index": 1, "text": "G", "emphasized": false}, {"index": 2, "text": "FR", "emphasized": false}, {"index": 3, "text": "6'5\"", "emphasized": false}, {"index": 4, "text": "190 lbs", "emphasized": false}], "isCutoff": false, "selected": false, "entityLink": {"title": "DREW SNIVELY", "webUrl": "/college-basketball/drew-snively-player", "color": "1, 156, 5, 47", "imageUrl": "https://b.fssta.com/uploads/application/college/team-logos/Indiana-alternate.vresize.200.200.medium.0.png", "imageType": "image-logo", "imageAltText": "Indiana Hoosiers", "contentUri": "basketball/cbk/athletes/81056", "contentType": "athlete", "layout": {"path": "/layouts?type=layout&subtype=playersLayout&elementId=cbk", "tokens": {"id": "81056", "contentUri": "basketball/cbk/athletes/81056"}}, "analyticsName": "drew-snively", "analyticsSport": "college-basketball", "type": "entity"}, "isFaded": false}, {"columns": [{"index": 0, "text": "Ian Stephens", "superscript": "#30", "emphasized": false}, {"index": 1, "text": "G", "emphasized": false}, {"index": 2, "text": "JR", "emphasized": false}, {"index": 3, "text": "6'5\"", "emphasized": false}, {"index": 4, "text": "180 lbs", "emphasized": false}], "isCutoff": false, "selected": false, "entityLink": {"title": "IAN STEPHENS", "webUrl": "/college-basketball/ian-stephens-player", "color": "1, 156, 5, 47", "imageUrl": "https://b.fssta.com/uploads/application/college/team-logos/Indiana-alternate.vresize.200.200.medium.0.png", "imageType": "image-logo", "imageAltText": "Indiana Hoosiers", "contentUri": "basketball/cbk/athletes/71467", "contentType": "athlete", "layout": {"path": "/layouts?type=layout&subtype=playersLayout&elementId=cbk", "tokens": {"id": "71467", "contentUri": "basketball/cbk/athletes/71467"}}, "analyticsName": "ian-stephens", "analyticsSport": "college-basketball", "type": "entity"}, "isFaded": false}, {"columns": [{"index": 0, "text": "Lamar Wilkerson", "superscript": "#3", "emphasized": false}, {"index": 1, "text": "G", "emphasized": false}, {"index": 2, "text": "SR", "emphasized": false}, {"index": 3, "text": "6'6\"", "emphasized": false}, {"index": 4, "text": "205 lbs", "emphasized": false}], "isCutoff": false, "selected": false, "entityLink": {"title": "LAMAR WILKERSON", "webUrl": "/college-basketball/lamar-wilkerson-player", "color": "1, 156, 5, 47", "imageUrl": "https://b.fssta.com/uploads/application/college/team-logos/Indiana-alternate.vresize.200.200.medium.0.png", "imageType": "image-logo", "imageAltText": "Indiana Hoosiers", "contentUri": "basketball/cbk/athletes/64707", "contentType": "athlete", "layout": {"path": "/layouts?type=layout&subtype=playersLayout&elementId=cbk", "tokens": {"id": "64707", "contentUri": "basketball/cbk/athletes/64707"}}, "analyticsName": "lamar-wilkerson", "analyticsSport": "college-basketball", "type": "entity"}, "isFaded": false}]}, {"template": "table-roster", "headers": [{"columns": [{"index": 0, "text": "FORWARD", "priority": 1, "template": "cell-entity-text", "weight": 4.9, "emphasized": true, "sortable": "none"}, {"index": 1, "text": "POS", "priority": 2, "template": "cell-text", "weight": 1, "emphasized": false, "sortable": "none"}, {"index": 2, "text": "CLS", "priority": 3, "template": "cell-text", "weight": 1.1, "emphasized": false, "sortable": "none"}, {"index": 3, "text": "HT", "priority": 4, "template": "cell-text", "weight": 1.2, "emphasized": false, "sortable": "none"}, {"index": 4, "text": "WT", "priority": 5, "template": "cell-text", "weight": 1.8, "emphasized": false, "sortable": "none"}], "isPrimary": true}], "rows": [{"columns": [{"index": 0, "text": "Sam Alexis", "superscript": "#4", "emphasized": false}, {"index": 1, "text": "F", "emphasized": false}, {"index": 2, "text": "SR", "emphasized": false}, {"index": 3, "text": "6'9\"", "emphasized": false}, {"index": 4, "text": "240 lbs", "emphasized": false}], "isCutoff": false, "selected": false, "entityLink": {"title": "SAM ALEXIS", "webUrl": "/college-basketball/sam-alexis-player", "color": "1, 156, 5, 47", "imageUrl": "https://b.fssta.com/uploads/application/college/team-logos/Indiana-alternate.vresize.200.200.medium.0.png", "imageType": "image-logo", "imageAltText": "Indiana Hoosiers", "contentUri": "basketball/cbk/athletes/64508", "contentType": "athlete", "layout": {"path": "/layouts?type=layout&subtype=playersLayout&elementId=cbk", "tokens": {"id": "64508", "contentUri": "basketball/cbk/athletes/64508"}}, "analyticsName": "sam-alexis", "analyticsSport": "college-basketball", "type": "entity"}, "isFaded": false}, {"columns": [{"index": 0, "text": "Reed Bailey", "superscript": "#1", "emphasized": false}, {"index": 1, "text": "F", "emphasized": false}, {"index": 2, "text": "SR", "emphasized": false}, {"index": 3, "text": "6'10\"", "emphasized": false}, {"index": 4, "text": "230 lbs", "emphasized": false}], "isCutoff": false, "selected": false, "entityLink": {"title": "REED BAILEY", "webUrl": "/college-basketball/reed-bailey-player", "color": "1, 156, 5, 47", "imageUrl": "https://b.fssta.com/uploads/application/college/team-logos/Indiana-alternate.vresize.200.200.medium.0.png", "imageType": "image-logo", "imageAltText": "Indiana Hoosiers", "contentUri": "basketball/cbk/athletes/65624", "contentType": "athlete", "layout": {"path": "/layouts?type=layout&subtype=playersLayout&elementId=cbk", "tokens": {"id": "65624", "contentUri": "basketball/cbk/athletes/65624"}}, "analyticsName": "reed-bailey", "analyticsSport": "college-basketball", "type": "entity"}, "isFaded": false}, {"columns": [{"index": 0, "text": "Tucker DeVries", "superscript": "#12", "emphasized": false}, {"index": 1, "text": "F", "emphasized": false}, {"index": 2, "text": "SR", "emphasized": false}, {"index": 3, "text": "6'7\"", "emphasized": false}, {"index": 4, "text": "225 lbs", "emphasized": false}], "isCutoff": false, "selected": false, "entityLink": {"title": "TUCKER DEVRIES", "webUrl": "/college-basketball/tucker-devries-player", "color": "1, 156, 5, 47", "imageUrl": "https://b.fssta.com/uploads/application/college/team-logos/Indiana-alternate.vresize.200.200.medium.0.png", "imageType": "image-logo", "imageAltText": "Indiana Hoosiers", "contentUri": "basketball/cbk/athletes/58842", "contentType": "athlete", "layout": {"path": "/layouts?type=layout&subtype=playersLayout&elementId=cbk", "tokens": {"id": "58842", "contentUri": "basketball/cbk/athletes/58842"}}, "analyticsName": "tucker-devries", "analyticsSport": "college-basketball", "type": "entity"}, "isFaded": false}, {"columns": [{"index": 0, "text": "Josh Harris", "superscript": "#10", "emphasized": false}, {"index": 1, "text": "F", "emphasized": false}, {"index": 2, "text": "SO", "emphasized": false}, {"index": 3, "text": "6'8\"", "emphasized": false}, {"index": 4, "text": "225 lbs", "emphasized": false}], "isCutoff": false, "selected": false, "entityLink": {"title": "JOSH HARRIS", "webUrl": "/college-basketball/josh-harris-4-player", "color": "1, 156, 5, 47", "imageUrl": "https://b.fssta.com/uploads/application/college/team-logos/Indiana-alternate.vresize.200.200.medium.0.png", "imageType": "image-logo", "imageAltText": "Indiana Hoosiers", "contentUri": "basketball/cbk/athletes/76518", "contentType": "athlete", "layout": {"path": "/layouts?type=layout&subtype=playersLayout&elementId=cbk", "tokens": {"id": "76518", "contentUri": "basketball/cbk/athletes/76518"}}, "analyticsName": "josh-harris-4", "analyticsSport": "college-basketball", "type": "entity"}, "isFaded": false}, {"columns": [{"index": 0, "text": "Trent Sisley", "superscript": "#11", "emphasized": false}, {"index": 1, "text": "F", "emphasized": false}, {"index": 2, "text": "FR", "emphasized": false}, {"index": 3, "text": "6'8\"", "emphasized": false}, {"index": 4, "text": "225 lbs", "emphasized": false}], "isCutoff": false, "selected": false, "entityLink": {"title": "TRENT SISLEY", "webUrl": "/college-basketball/trent-sisley-player", "color": "1, 156, 5, 47", "imageUrl": "https://b.fssta.com/uploads/application/college/team-logos/Indiana-alternate.vresize.200.200.medium.0.png", "imageType": "image-logo", "imageAltText": "Indiana Hoosiers", "contentUri": "basketball/cbk/athletes/81043", "contentType": "athlete", "layout": {"path": "/layouts?type=layout&subtype=playersLayout&elementId=cbk", "tokens": {"id": "81043", "contentUri": "basketball/cbk/athletes/81043"}}, "analyticsName": "trent-sisley", "analyticsSport": "college-basketball", "type": "entity"}, "isFaded": false}]}, {"template": "table-roster", "headers": [{"columns": [{"index": 0, "text": "CENTER", "priority": 1, "template": "cell-entity-text", "weight": 4.9, "emphasized": true, "sortable": "none"}, {"index": 1, "text": "POS", "priority": 2, "template": "cell-text", "weight": 1, "emphasized": false, "sortable": "none"}, {"index": 2, "text": "CLS", "priority": 3, "template": "cell-text", "weight": 1.1, "emphasized": false, "sortable": "none"}, {"index": 3, "text": "HT", "priority": 4, "template": "cell-text", "weight": 1.2, "emphasized": false, "sortable": "none"}, {"index": 4, "text": "WT", "priority": 5, "template": "cell-text", "weight": 1.8, "emphasized": false, "sortable": "none"}], "isPrimary": true}], "rows": [{"columns": [{"index": 0, "text": "Andrej Acimovic", "superscript": "#15", "emphasized": false}, {"index": 1, "text": "C", "emphasized": false}, {"index": 2, "text": "FR", "emphasized": false}, {"index": 3, "text": "6'10\"", "emphasized": false}, {"index": 4, "text": "240 lbs", "emphasized": false}], "isCutoff": false, "selected": false, "entityLink": {"title": "ANDREJ ACIMOVIC", "webUrl": "/college-basketball/andrej-acimovic-player", "color": "1, 156, 5, 47", "imageUrl": "https://b.fssta.com/uploads/application/college/team-logos/Indiana-alternate.vresize.200.200.medium.0.png", "imageType": "image-logo", "imageAltText": "Indiana Hoosiers", "contentUri": "basketball/cbk/athletes/81055", "contentType": "athlete", "layout": {"path": "/layouts?type=layout&subtype=playersLayout&elementId=cbk", "tokens": {"id": "81055", "contentUri": "basketball/cbk/athletes/81055"}}, "analyticsName": "andrej-acimovic", "analyticsSport": "college-basketball", "type": "entity"}, "isFaded": false}]}, {"template": "table-roster", "headers": [{"columns": [{"index": 0, "text": "PLAYER COUNT", "priority": 1, "template": "cell-text", "weight": 2.5, "emphasized": true, "sortable": "none"}, {"index": 1, "priority": 5, "template": "cell-text", "weight": 2.5, "emphasized": false, "sortable": "none", "hideView": 1}, {"index": 2, "text": "AVG AGE", "priority": 2, "template": "cell-text", "weight": 2.5, "emphasized": false, "sortable": "none"}, {"index": 3, "text": "AVG HT", "priority": 3, "template": "cell-text", "weight": 2.5, "emphasized": false, "sortable": "none"}, {"index": 4, "text": "AVG WT", "priority": 4, "template": "cell-text", "weight": 2.5, "emphasized": false, "sortable": "none"}], "isPrimary": true}], "rows": [{"columns": [{"index": 0, "text": "17", "emphasized": false}, {"index": 1, "emphasized": false}, {"index": 2, "text": "-", "emphasized": false}, {"index": 3, "text": "6'5\"", "emphasized": false}, {"index": 4, "text": "208.8 lbs", "emphasized": false}], "isCutoff": false, "selected": false, "isFaded": false}]}]}